{
    "name": "Parent",
    "type": "Obj",
    "nullable": "y",
    "children": [
      {
        "name": "Child 1",
        "type": "Array",
        "nullable": "y",            
        "children": [
          {
            "name": "Grandchild 1"
          },
          {
            "name": "Grandchild 2"
          }
        ]
      },
      {
        "name": "Child 2",
        "children": [
          {
            "name": "Grandchild 3"
          },
          {
            "name": "Grandchild 4"
          }
        ]
      }
    ]
  }